<?xml version="1.0" encoding="utf-8" ?>
<c2eventsheet>
    <!--All the 'name' attributes are ignored by Construct 2 - they are there for readability only.-->
    <name>Event sheet 4</name>
    <events>
        <event-group description="" sid="603755353815183" title="Timer2">
            <sub-events>
                <event-block sid="324553572069304">
                    <conditions>
                        <condition id="-6" name="Every X seconds" sid="174671526106968" type="System">
                            <param id="0" name="Interval (seconds)">5</param>
                        </condition>
                        <condition id="-14" name="Compare variable" sid="829635057648808" type="System">
                            <param id="0" name="Variable">Tracker</param>
                            <param id="1" name="Comparison">2</param>
                            <param id="2" name="Value">6</param>
                        </condition>
                    </conditions>
                    <actions>
                        <action id="0" name="Play" sid="635465725391612" type="Audio">
                            <param id="0" name="Audio file">quiet_pig</param>
                            <param id="2" name="Loop">0</param>
                            <param id="3" name="Volume">0</param>
                            <param id="1" name="Tag (optional)">&quot;pig&quot;</param>
                        </action>
                        <action id="3" name="Set volume" sid="359514241260591" type="Audio">
                            <param id="0" name="Tag">&quot;bg&quot;</param>
                            <param id="1" name="dB">-10</param>
                        </action>
                    </actions>
                </event-block>
                <event-block sid="365770054346738">
                    <conditions>
                        <condition id="-6" name="Every X seconds" sid="285472840739019" type="System">
                            <param id="0" name="Interval (seconds)">1.0</param>
                        </condition>
                        <condition id="-14" name="Compare variable" sid="470939516994093" type="System">
                            <param id="0" name="Variable">Tracker</param>
                            <param id="1" name="Comparison">2</param>
                            <param id="2" name="Value">6</param>
                        </condition>
                    </conditions>
                    <actions>
                        <action id="-10" name="Add to" sid="587203259041880" type="System">
                            <param id="0" name="Variable">FinalSecond</param>
                            <param id="1" name="Value">1</param>
                        </action>
                    </actions>
                </event-block>
                <event-block sid="359591900881391">
                    <conditions>
                        <condition id="-14" name="Compare variable" sid="207544615591319" type="System">
                            <param id="0" name="Variable">FinalSecond</param>
                            <param id="1" name="Comparison">0</param>
                            <param id="2" name="Value">60</param>
                        </condition>
                        <condition id="-14" name="Compare variable" sid="481787727931571" type="System">
                            <param id="0" name="Variable">Tracker</param>
                            <param id="1" name="Comparison">2</param>
                            <param id="2" name="Value">6</param>
                        </condition>
                    </conditions>
                    <actions>
                        <action id="-9" name="Set value" sid="344617630768988" type="System">
                            <param id="0" name="Variable">FinalSecond</param>
                            <param id="1" name="Value">0</param>
                        </action>
                        <action id="-10" name="Add to" sid="716461242596714" type="System">
                            <param id="0" name="Variable">FinalMinute</param>
                            <param id="1" name="Value">1</param>
                        </action>
                    </actions>
                </event-block>
                <event-block sid="619300038471463">
                    <conditions>
                        <condition id="-14" name="Compare variable" sid="399671005861560" type="System">
                            <param id="0" name="Variable">FinalSecond</param>
                            <param id="1" name="Comparison">2</param>
                            <param id="2" name="Value">60</param>
                        </condition>
                        <condition id="-14" name="Compare variable" sid="505606342586627" type="System">
                            <param id="0" name="Variable">Tracker</param>
                            <param id="1" name="Comparison">2</param>
                            <param id="2" name="Value">6</param>
                        </condition>
                    </conditions>
                    <actions>
                        <action id="0" name="Set text" sid="753216585077732" type="second2">
                            <param id="0" name="Text">FinalSecond</param>
                        </action>
                        <action id="0" name="Set text" sid="329820763102882" type="minute2">
                            <param id="0" name="Text">FinalMinute</param>
                        </action>
                    </actions>
                </event-block>
                <event-block sid="449750112091785">
                    <conditions>
                        <condition id="-14" name="Compare variable" sid="189464441745125" type="System">
                            <param id="0" name="Variable">Tracker</param>
                            <param id="1" name="Comparison">0</param>
                            <param id="2" name="Value">6</param>
                        </condition>
                    </conditions>
                    <actions>
                        <action id="-2" name="Set Y" sid="793112008389585" type="second2">
                            <param id="0" name="Y">268</param>
                        </action>
                        <action id="-2" name="Set Y" sid="545060143790175" type="minute2">
                            <param id="0" name="Y">268</param>
                        </action>
                        <action id="-2" name="Set Y" sid="806220302330865" type="colon">
                            <param id="0" name="Y">268</param>
                        </action>
                        <action id="-2" name="Set Y" sid="711098213740036" type="minute1">
                            <param id="0" name="Y">268</param>
                        </action>
                        <action id="-2" name="Set Y" sid="168109809739427" type="second1">
                            <param id="0" name="Y">268</param>
                        </action>
                    </actions>
                </event-block>
                <event-block sid="486947171049247">
                    <conditions>
                        <condition id="-14" name="Compare variable" sid="869744220343699" type="System">
                            <param id="0" name="Variable">FinalSecond</param>
                            <param id="1" name="Comparison">2</param>
                            <param id="2" name="Value">10</param>
                        </condition>
                    </conditions>
                    <actions>
                        <action id="-15" name="Set visible" sid="816576148918869" type="second1">
                            <param id="0" name="Visibility">1</param>
                        </action>
                    </actions>
                </event-block>
                <event-block sid="264240255693077">
                    <conditions>
                        <condition id="-14" name="Compare variable" sid="400114641667062" type="System">
                            <param id="0" name="Variable">FinalSecond</param>
                            <param id="1" name="Comparison">5</param>
                            <param id="2" name="Value">10</param>
                        </condition>
                    </conditions>
                    <actions>
                        <action id="-15" name="Set visible" sid="555880298809470" type="second1">
                            <param id="0" name="Visibility">0</param>
                        </action>
                    </actions>
                </event-block>
                <event-block sid="360126796930561">
                    <conditions>
                        <condition id="-14" name="Compare variable" sid="142798119679049" type="System">
                            <param id="0" name="Variable">FinalMinute</param>
                            <param id="1" name="Comparison">2</param>
                            <param id="2" name="Value">10</param>
                        </condition>
                    </conditions>
                    <actions>
                        <action id="-15" name="Set visible" sid="217174539238283" type="minute1">
                            <param id="0" name="Visibility">1</param>
                        </action>
                    </actions>
                </event-block>
                <event-block sid="504179311582528">
                    <conditions>
                        <condition id="-14" name="Compare variable" sid="665158253516955" type="System">
                            <param id="0" name="Variable">FinalMinute</param>
                            <param id="1" name="Comparison">5</param>
                            <param id="2" name="Value">10</param>
                        </condition>
                    </conditions>
                    <actions>
                        <action id="-15" name="Set visible" sid="902432814690073" type="minute1">
                            <param id="0" name="Visibility">0</param>
                        </action>
                    </actions>
                </event-block>
            </sub-events>
        </event-group>
    </events>
</c2eventsheet>
